benchmarks/__init__.py
py_rankaggregation/__init__.py
py_rankaggregation/geomeanrankaggregator.py
py_rankaggregation/meanrankaggregator.py
py_rankaggregation/medianrankaggregator.py
py_rankaggregation/rankaggregator.py
py_rankaggregation/tests/__init__.py
py_rankaggregation/tests/test_geomean_rank_aggregator.py
py_rankaggregation/tests/test_mean_rank_aggregator.py
py_rankaggregation/tests/test_median_rank_aggregator.py
py_rankaggregation/utils/__init__.py
py_rankaggregation/utils/generic_helper.py
py_rankaggregation/utils/stop_words.txt
py_rankaggregation-0.1.2.dist-info/LICENSE
py_rankaggregation-0.1.2.dist-info/METADATA
py_rankaggregation-0.1.2.dist-info/WHEEL
py_rankaggregation-0.1.2.dist-info/top_level.txt
py_rankaggregation-0.1.2.dist-info/RECORD
